dilcher_configuration/__init__.py
dilcher_configuration/apps.py
dilcher_configuration/mixins.py
dilcher_configuration/models.py
dilcher_configuration/test_models.py
dilcher_configuration-0.6.5.dist-info/LICENSE
dilcher_configuration-0.6.5.dist-info/METADATA
dilcher_configuration-0.6.5.dist-info/WHEEL
dilcher_configuration-0.6.5.dist-info/top_level.txt
dilcher_configuration-0.6.5.dist-info/RECORD
