Metadata-Version: 2.1
Name: dilcher-configuration
Version: 0.6.5
Summary: The dilcher-configuration Django app is used to provide easily manageable settings for Django projects.
Home-page: https://github.com/cdilcher/dilcher-configuration
Author: Philipp Freyer
Author-email: philipp.freyer@dilcher.de
Classifier: Programming Language :: Python :: 3
Classifier: License :: OSI Approved :: Apache Software License
Classifier: Operating System :: OS Independent
Requires-Python: >=3.6
License-File: LICENSE
Requires-Dist: Django >=3.0.0
